protocol_helper/__init__.py
protocol_helper/setting.py
protocol_helper/exceptions/__init__.py
protocol_helper/exceptions/_abnormal.py
protocol_helper/exceptions/_request_exceptions.py
protocol_helper/services/BiLiCollectionService.py
protocol_helper/services/DouYinPcCollectionService.py
protocol_helper/services/MonitoringCenterService.py
protocol_helper/services/PPPOEService.py
protocol_helper/services/QuanMingCollectionService.py
protocol_helper/services/SouHuCollectionService.py
protocol_helper/services/TouTiaoCollectionService.py
protocol_helper/services/WeChatCollectionService.py
protocol_helper/services/WeiBoAppCollectionService.py
protocol_helper/services/WeiBoBaseService.py
protocol_helper/services/WeiBoH5collectionService.py
protocol_helper/services/WeiBoPcCollectionService.py
protocol_helper/services/XiaoHongShuCollectionService.py
protocol_helper/services/ZhiBoCollectionService.py
protocol_helper/services/__init__.py
protocol_helper/utils/Log.py
protocol_helper/utils/__init__.py
protocol_helper/utils/request.py
protocol_helper/utils/tools.py
protocol_helper-0.2.0.dist-info/LICENSE
protocol_helper-0.2.0.dist-info/METADATA
protocol_helper-0.2.0.dist-info/WHEEL
protocol_helper-0.2.0.dist-info/top_level.txt
protocol_helper-0.2.0.dist-info/RECORD
